caspailleur/__init__.py
caspailleur/api.py
caspailleur/base_functions.py
caspailleur/definitions.py
caspailleur/implication_bases.py
caspailleur/indices.py
caspailleur/io.py
caspailleur/mine_equivalence_classes.py
caspailleur/orchestrator.py
caspailleur/order.py
caspailleur-0.2.2.dist-info/licenses/LICENSE
tests/test_api.py
tests/test_base_functions.py
tests/test_definitions.py
tests/test_implication_bases.py
tests/test_indices.py
tests/test_io.py
tests/test_mine_equivalence_classes.py
tests/test_orchestrator.py
tests/test_order.py
tests/test_readme.py
venv/bin/activate_this.py
caspailleur-0.2.2.dist-info/METADATA
caspailleur-0.2.2.dist-info/WHEEL
caspailleur-0.2.2.dist-info/top_level.txt
caspailleur-0.2.2.dist-info/RECORD
