Metadata-Version: 2.4
Name: caspailleur
Version: 0.2.2
Summary: Minimalistic python package for mining many concise data representations. Part of SmartFCA project
Author: Egor Dudyrev
License:                     GNU GENERAL PUBLIC LICENSE
Project-URL: Homepage, https://github.com/smartFCA/caspailleur
Keywords: python,fca,itemset-mining
Classifier: Programming Language :: Python :: 3
Classifier: Programming Language :: Python :: 3.8
Classifier: License :: OSI Approved :: GNU General Public License v3 (GPLv3)
Classifier: Operating System :: OS Independent
Requires-Python: >=3.8
License-File: LICENSE
Requires-Dist: numpy>=1.20
Requires-Dist: scikit-mine>=1
Requires-Dist: bitarray>=3.0.0
Requires-Dist: tqdm
Requires-Dist: deprecation
Requires-Dist: PyYAML
Dynamic: license-file
